{
  "title": "斗罗大陆动漫第八集改动了这些细节，原著粉们都发现了吗?",
  "date": 1520294400000,
  "url": "https://mp.weixin.qq.com/s?__biz=MzIwOTI5MDc1Mg==&mid=2650187298&idx=2&sn=8f46ba911e6ba80872e32beca5270035&chksm=8f74154db8039c5b6ad0c7c300c8a37ce9c8a41852db1d21ace986f951b3cd19cbb12d447d53&scene=38#wechat_redirect",
  "article": [
    {
      "p": "现在《斗罗大陆》第八集已经在腾讯视频播出了，开通腾讯视频VIP的小伙伴已经可以提前观看第八集。在这部号称高度还原的作品中，其实还是有一些和原著不同，在更新的第八集中就改动了这些设定，不知道有多少原著粉发现其中的不同之处呢?"
    },
    {
      "p": "大师中毒："
    },
    {
      "p": "在这一集中唐三在融合他的第一武魂之后，醒来后的唐三发现大师正躺在一旁，看他的脸色似乎是中毒的迹象，看到大师中毒了之后唐三也是立马帮大师解毒。"
    },
    {
      "img": {
        "src": "https://mmbiz.qpic.cn/mmbiz_jpg/Qodb7ohzYcn6jcERS0C4h1G8JzkmjQ3STa4XtQtEB2oI7KGD6ztLKj21D6R5YJjtKria0grp9BB63zvfjxzgqqA/640?wx_fmt=jpeg",
        "width": 670,
        "height": 448
      }
    },
    {
      "p": "在动漫中少了老师自己处理伤口的说明，还有就是唐三帮大师解毒的时候，小说里唐三曾经挖坑用来处理大师体内逼出来的毒。还有就是唐三帮大师解毒的时候，应该是在三处划开了放血口，分别是脉门、臂弯、腋下。除此之外，在他们离开猎魂森林的时候，大师应该是被唐三背出去的，而不是和唐三并肩走出去。"
    },
    {
      "img": {
        "src": "https://mmbiz.qpic.cn/mmbiz_jpg/Qodb7ohzYcn6jcERS0C4h1G8JzkmjQ3S86W2xHVyUrDniaEemmUPd7ibxHwuwfUNx4pnvtvtVtvMPncT5dqojAUQ/640?wx_fmt=jpeg",
        "width": 668,
        "height": 467
      }
    },
    {
      "p": "绅士君之所以要抓这一点说，因为在小说中正是因为这件事情，大师对唐三的态度发生了一个转变。在这之前，大师一直把唐三当做是一个帮助自己完成梦想的徒弟，但是经历过这件事情之后，他看待唐三的眼神已经和唐昊一样了，当初唐三拜师时那一句“一日为师，终身为父”更加深刻的印在大师的脑海中。"
    },
    {
      "img": {
        "src": "https://mmbiz.qpic.cn/mmbiz_jpg/Qodb7ohzYcn6jcERS0C4h1G8JzkmjQ3SmltUZEmPDKicqbskN7mhnTgtVsiaaVxFPN2iawcibWFmtDJq0D2vKdZVRA/640?wx_fmt=jpeg",
        "width": 668,
        "height": 426
      }
    },
    {
      "p": "武魂鉴定："
    },
    {
      "p": "在唐三处理完工读生和萧老大之间的恩怨后，按照大师的吩咐前往武魂殿进行武魂鉴定，在武魂殿中他碰到了帮他觉醒武魂的素云涛，此时他正在和负责武魂鉴定的马修诺大师聊天。在看到唐三之后，他将唐三托付给马修诺大师就离开了。"
    },
    {
      "img": {
        "src": "https://mmbiz.qpic.cn/mmbiz_jpg/Qodb7ohzYcn6jcERS0C4h1G8JzkmjQ3SyKNkMejkJO0G1GiaXs7cqRmtoEyeuFYpKAbgx6vZeyEzqibChzGqgMMg/640?wx_fmt=jpeg",
        "width": 668,
        "height": 457
      }
    },
    {
      "p": "而小说中，唐三虽然也是先遇到了素云涛，可是唐三遇到他的时候他正在和一个女魂师聊天，随着他才带着唐三去找到了马修诺大师。"
    },
    {
      "img": {
        "src": "https://mmbiz.qpic.cn/mmbiz_jpg/Qodb7ohzYcn6jcERS0C4h1G8JzkmjQ3SFhGEeYHbLpYQDicZDrbaia9CwIwiczQcI0feWRWRyTBAHl3vKiabrK2pyA/640?wx_fmt=jpeg",
        "width": 668,
        "height": 466
      }
    },
    {
      "p": "除了这两处之外，在第八集的三个场景中，也只有唐三他们和萧老大的那一场的还原度最高，不过虽然动画中有很多小说的细节没有照顾到，但是能够制作成这样也实属不易，至少比《斗破苍穹》第一季好太多!"
    },
    {
      "p": "谢谢大家!!!我是绅士君，一个gay里gay气的绅士，每天都会为大家带来不一样的动漫解答，欢迎大家前排吃瓜，顺便给个关注吧!"
    }
  ]
}